Metadata-Version: 1.2
Name: sandpaper
Version: 0.0.6
Summary: Simplified table-type data normalization
Home-page: https://github.com/stephen-bunn/sandpaper
Author: Stephen Bunn
Author-email: stephen@bunn.io
License: MIT License
Keywords: normalize,csv,excel,table,clean
Platform: UNKNOWN
Classifier: Development Status :: 2 - Pre-Alpha
Classifier: Programming Language :: Python :: 2.7
Classifier: Programming Language :: Python :: 3
Classifier: Programming Language :: Python :: 3.3
Classifier: Programming Language :: Python :: 3.4
Classifier: Programming Language :: Python :: 3.5
Classifier: Programming Language :: Python :: 3.6
Classifier: License :: OSI Approved :: MIT License
Classifier: Intended Audience :: Developers
Classifier: Intended Audience :: System Administrators
Classifier: Operating System :: POSIX
Classifier: Operating System :: MacOS :: MacOS X
Classifier: Natural Language :: English
Classifier: Topic :: Software Development :: Pre-processors
Classifier: Topic :: Software Development :: Quality Assurance
Requires-Python: >=2.7
